accomate/__init__.py
accomate/accomate.py
accomate/aws/route53.py
accomate/aws/s3.py
accomate/clis/database.py
accomate/conf/nginx.conf
accomate/conf/nginx/site.conf
accomate/data/accomate_config.py
accomate/scripts/docker-compose-install.sh
accomate/scripts/docker-install.sh
accomate/utils/command.py
accomate/utils/compose.py
accomate/utils/config.py
accomate/utils/dns.py
accomate/utils/domain.py
accomate/utils/echo.py
accomate/utils/env.py
accomate/utils/git.py
accomate/utils/keys.py
accomate/utils/network.py
accomate/utils/nginx.py
accomate/utils/passwords.py
accomate/utils/store.py
accomate/utils/validators.py
accomate/utils/wait.py
accomate/utils/yaml_file.py
accomate-2.0.0.6.dist-info/LICENSE.txt
accomate-2.0.0.6.dist-info/METADATA
accomate-2.0.0.6.dist-info/WHEEL
accomate-2.0.0.6.dist-info/entry_points.txt
accomate-2.0.0.6.dist-info/top_level.txt
accomate-2.0.0.6.dist-info/RECORD
