Metadata-Version: 2.1
Name: accomate
Version: 2.0.0.6
Summary: Accoladez + Automate = Accomate
Home-page: https://github.com/Accoladez/Accomate
Author: Accoladez
Author-email: vaibhav@itday.in
License-File: LICENSE.txt
Requires-Dist: anyio (==3.6.1)
Requires-Dist: astroid (==2.11.6)
Requires-Dist: attrs (==21.4.0)
Requires-Dist: autopep8 (==1.6.0)
Requires-Dist: beautifulsoup4 (==4.11.1)
Requires-Dist: bleach (==5.0.0)
Requires-Dist: boto3 (==1.24.2)
Requires-Dist: botocore (==1.27.2)
Requires-Dist: build (==0.8.0)
Requires-Dist: certifi (==2022.5.18.1)
Requires-Dist: cffi (==1.15.0)
Requires-Dist: charset-normalizer (==2.0.12)
Requires-Dist: click (==8.1.3)
Requires-Dist: cloudflare (==2.9.10)
Requires-Dist: commonmark (==0.9.1)
Requires-Dist: cryptography (==37.0.2)
Requires-Dist: dill (==0.3.5.1)
Requires-Dist: docker (==5.0.3)
Requires-Dist: docutils (==0.18.1)
Requires-Dist: feedparser (==6.0.10)
Requires-Dist: fire (==0.4.0)
Requires-Dist: flake8 (==4.0.1)
Requires-Dist: h11 (==0.12.0)
Requires-Dist: html2text (==2020.1.16)
Requires-Dist: httpcore (==0.15.0)
Requires-Dist: httpx (==0.23.0)
Requires-Dist: idna (==3.3)
Requires-Dist: importlib-metadata (==4.11.4)
Requires-Dist: isort (==5.10.1)
Requires-Dist: jeepney (==0.8.0)
Requires-Dist: jmespath (==1.0.0)
Requires-Dist: jsonlines (==3.0.0)
Requires-Dist: keyring (==23.6.0)
Requires-Dist: lazy-object-proxy (==1.7.1)
Requires-Dist: mccabe (==0.6.1)
Requires-Dist: packaging (==21.3)
Requires-Dist: pep517 (==0.12.0)
Requires-Dist: pkginfo (==1.8.3)
Requires-Dist: platformdirs (==2.5.2)
Requires-Dist: pycodestyle (==2.8.0)
Requires-Dist: pycparser (==2.21)
Requires-Dist: pycryptodome-test-vectors (==1.0.8)
Requires-Dist: pycryptodomex (==3.14.1)
Requires-Dist: pyflakes (==2.4.0)
Requires-Dist: Pygments (==2.12.0)
Requires-Dist: pylint (==2.14.1)
Requires-Dist: pymongo (==4.1.1)
Requires-Dist: pyparsing (==3.0.9)
Requires-Dist: python-dateutil (==2.8.2)
Requires-Dist: python-dotenv (==0.20.0)
Requires-Dist: PyYAML (==6.0)
Requires-Dist: randomname (==0.1.5)
Requires-Dist: readme-renderer (==35.0)
Requires-Dist: requests (==2.27.1)
Requires-Dist: requests-toolbelt (==0.9.1)
Requires-Dist: rfc3986 (==1.5.0)
Requires-Dist: rich (==12.4.4)
Requires-Dist: s3transfer (==0.6.0)
Requires-Dist: SecretStorage (==3.3.2)
Requires-Dist: sgmllib3k (==1.0.0)
Requires-Dist: six (==1.16.0)
Requires-Dist: sniffio (==1.2.0)
Requires-Dist: soupsieve (==2.3.2.post1)
Requires-Dist: termcolor (==1.1.0)
Requires-Dist: toml (==0.10.2)
Requires-Dist: tomli (==2.0.1)
Requires-Dist: tomlkit (==0.11.0)
Requires-Dist: twine (==4.0.1)
Requires-Dist: typer (==0.4.1)
Requires-Dist: urllib3 (==1.26.9)
Requires-Dist: webencodings (==0.5.1)
Requires-Dist: websocket-client (==1.3.2)
Requires-Dist: wrapt (==1.14.1)
Requires-Dist: zipp (==3.8.0)
